[
  {
    "id": "02",
    "talk": [
      "トーク1つ目のテキストトーク1つ目のテキストトーク1つ目のテキストトーク1つ目のテキストトーク1つ目のテキストトーク1つ目のテキスト",
      "トーク2つ目のテキストトーク2つ目のテキストトーク2つ目のテキストトーク2つ目のテキストトーク2つ目のテキストトーク2つ目のテキスト",
      "トーク3つ目のテキストトーク3つ目のテキストトーク3つ目のテキストトーク3つ目のテキストトーク3つ目のテキストトーク3つ目のテキスト"
    ],
    "talkAnswer": [
      [
        "トーク1つ目の解答-1",
        "トーク1つ目の解答-2",
        "トーク1つ目の解答-3"
      ],
      [
        "トーク2つ目の解答-1",
        "トーク2つ目の解答-2",
        "トーク2つ目の解答-3"
      ],
      [
        "トーク3つ目の解答-1",
        "トーク3つ目の解答-2",
        "トーク3つ目の解答-3"
      ]
    ],
    "quiz": [
      "トーク1つ目の場合のテキスト",
      "トーク2つ目の場合のテキスト",
      "トーク3つ目の場合のテキスト"
    ],
    "quizText": "クイズ固定のテキストクイズ固定の問題テキストクイズ固定の問題テキストクイズ固定の問題テキストクイズ固定の問題テキスト",
    "quizChoice": [
      "quizChoice1",
      "quizChoice2",
      "quizChoice3"
    ],
    "quizAnswer": 2
  }
]